ine_mcp/__init__.py
ine_mcp/server.py
ine_mcp-0.1.3.dist-info/licenses/LICENSE
ine_mcp-0.1.3.dist-info/METADATA
ine_mcp-0.1.3.dist-info/WHEEL
ine_mcp-0.1.3.dist-info/entry_points.txt
ine_mcp-0.1.3.dist-info/top_level.txt
ine_mcp-0.1.3.dist-info/RECORD
